lemma/__init__.py
lemma/cmdline.py
lemma/core.hy
lemma/docmd.hy
lemma/exceptions.hy
lemma/ipython.py
lemma/lang.hy
lemma/precedence.hy
lemma/utils.hy
lemma/domain/__init__.hy
lemma/domain/algebra.hy
tests/__init__.py
tests/test_utils.hy
lemma-1.0.3.dist-info/LICENSE
lemma-1.0.3.dist-info/METADATA
lemma-1.0.3.dist-info/WHEEL
lemma-1.0.3.dist-info/entry_points.txt
lemma-1.0.3.dist-info/top_level.txt
lemma-1.0.3.dist-info/RECORD
