Metadata-Version: 2.1
Name: lemma
Version: 1.0.3
Summary: An extensible mini-language to generate mathematical notation for executable and testable Python.
Home-page: https://github.com/ben-denham/lemma
Author: Ben Denham
Author-email: ben@denham.nz
License: UNKNOWN
Platform: UNKNOWN
Classifier: Development Status :: 2 - Pre-Alpha
Classifier: Intended Audience :: Developers
Classifier: Intended Audience :: Education
Classifier: Intended Audience :: Science/Research
Classifier: License :: OSI Approved :: BSD License
Classifier: Operating System :: OS Independent
Classifier: Programming Language :: Python :: 3
Classifier: Topic :: Scientific/Engineering :: Mathematics
Requires-Python: >=3.6
Requires-Dist: hy (>=0.18.0)
Provides-Extra: dev
Requires-Dist: flake8 (>=3.7.9) ; extra == 'dev'
Requires-Dist: pytest (>=5.2.2) ; extra == 'dev'
